ipyprogressbar/__init__.py
ipyprogressbar/ipyprogressbar.py
ipyprogressbar-1.0.2.dist-info/METADATA
ipyprogressbar-1.0.2.dist-info/RECORD
ipyprogressbar-1.0.2.dist-info/WHEEL
ipyprogressbar-1.0.2.dist-info/top_level.txt
