Metadata-Version: 2.1
Name: ipyprogressbar
Version: 1.0.2
Summary: Python-asynchronous progressbar widgets for use in Jupyter/IPython in conjunction with ipywidgets
Home-page: https://github.com/WillahScott/ipyprogressbar
Author: WillahScott
License: MIT
Project-URL: Say Thanks!, https://saythanks.io/to/WillahScott
Project-URL: Bug Reports, https://github.com/WillahScott/ipyprogressbar/issues
Keywords: widget jupyter progressbar asynchronous
Platform: UNKNOWN
Classifier: Intended Audience :: Developers
Classifier: Intended Audience :: Science/Research
Classifier: Topic :: Software Development :: Build Tools
Classifier: License :: OSI Approved :: MIT License
Classifier: Programming Language :: Python
Classifier: Programming Language :: Python :: 2.7
Classifier: Programming Language :: Python :: 3
Classifier: Programming Language :: Python :: 3.3
Classifier: Programming Language :: Python :: 3.4
Classifier: Programming Language :: Python :: 3.5
Classifier: Framework :: Jupyter
